{
  "January": {
    "id1": { "name": "Sayed", "points": 50 },
    "id2": { "name": "Mahmoud", "points": 60 },
    "id3": { "name": "Ali", "points": 20 }
  },
  "February": {
    "id1": { "name": "Sayed", "points": 70 },
    "id2": { "name": "Mahmoud", "points": 80 },
    "id3": { "name": "Ali", "points": 500 },
    "id4": { "name": "Osama", "points": 100 }
  },
  "March": {
    "id1": { "name": "Sayed", "points": 90 },
    "id2": { "name": "Mahmoud", "points": 100 },
    "id3": { "name": "Ali", "points": 500 }
  },
  "April": {
    "id1": { "name": "Sayed", "points": 50 },
    "id2": { "name": "Mahmoud", "points": 60 },
    "id3": { "name": "Ali", "points": 10 },
    "id4": { "name": "Osama", "points": 100 }
  },
  "May": {
    "id1": { "name": "Sayed", "points": 50 },
    "id2": { "name": "Mahmoud", "points": 60 },
    "id3": { "name": "Ali", "points": 40 }
  },
  "June": {
    "id1": { "name": "Sayed", "points": 50 },
    "id2": { "name": "Mahmoud", "points": 60 },
    "id3": { "name": "Ali", "points": 500 },
    "id4": { "name": "Osama", "points": 100 }
  },
  "July": {
    "id1": { "name": "Sayed", "points": 50 },
    "id2": { "name": "Mahmoud", "points": 60 },
    "id3": { "name": "Ali", "points": 10 }
  },
  "August": {
    "id1": { "name": "Sayed", "points": 50 },
    "id2": { "name": "Mahmoud", "points": 60 },
    "id4": { "name": "Osama", "points": 100 },
    "id3": { "name": "Ali", "points": 5 }
  },
  "September": {
    "id1": { "name": "Sayed", "points": 50 },
    "id2": { "name": "Mahmoud", "points": 60 },
    "id3": { "name": "Ali", "points": 500 }
  },
  "October": {
    "id1": { "name": "Sayed", "points": 50 },
    "id2": { "name": "Mahmoud", "points": 60 },
    "id3": { "name": "Ali", "points": 0 }
  },
  "November": {
    "id1": { "name": "Sayed", "points": 50 },
    "id2": { "name": "Mahmoud", "points": 60 },
    "id3": { "name": "Ali", "points": 0 }
  },
  "December": {
    "id1": { "name": "Sayed", "points": 50 },
    "id2": { "name": "Mahmoud", "points": 60 },
    "id3": { "name": "Ali", "points": 10 }
  }
}
